timerdo/__init__.py
timerdo/config.py
timerdo/core.py
timerdo/database.py
timerdo/exceptions.py
timerdo/main.py
timerdo/models.py
timerdo-0.0.5.dist-info/entry_points.txt
timerdo-0.0.5.dist-info/WHEEL
timerdo-0.0.5.dist-info/METADATA
timerdo-0.0.5.dist-info/RECORD
