Metadata-Version: 2.1
Name: timerdo
Version: 0.0.5
Summary: Minimalist to-do list with built-in timer to keep your tasks on track.
Author-email: Caio Mescouto Terra de Souza <caiomescouto@gmail.com>
Requires-Python: >=3.11
Requires-Dist: sqlalchemy >=2.0.4, <2.1
Requires-Dist: typer >=0.7.0, <0.9
Requires-Dist: rich >=13.3, <13.4
Requires-Dist: pandas[performance,feather] >=2.0.1, <2.1
Requires-Dist: black >=23.1, <23.2 ; extra == "dev"
Requires-Dist: flake8 >=6.0, <6.1 ; extra == "dev"
Requires-Dist: isort >=5.12, <5.13 ; extra == "dev"
Requires-Dist: pydocstyle[toml] >=6.3.0, <6.4 ; extra == "dev"
Requires-Dist: mkdocs-material >=9.1.3, <9.2 ; extra == "docs"
Requires-Dist: mkdocstrings[python] >=0.20, <0.21 ; extra == "docs"
Requires-Dist: mkdocs-git-revision-date-localized-plugin >=1.2.0, <1.3 ; extra == "docs"
Requires-Dist: typer-cli >=0.0.13, <0.1 ; extra == "docs"
Requires-Dist: pytest >=7.2.1, <7.3 ; extra == "test"
Requires-Dist: pytest-cov >=4.0.0, <4.1 ; extra == "test"
Requires-Dist: Faker >=17.6.0, <17.7 ; extra == "test"
Project-URL: Documentation, http://caiomts.github.io/timerdo
Project-URL: Source, https://github.com/caiomts/timerdo
Provides-Extra: dev
Provides-Extra: docs
Provides-Extra: test
